pconsole/Hermit-Regular.otf
pconsole/TerminusTTF-4.47.0.ttf
pconsole/TerminusTTF-Bold.ttf
pconsole/__init__.py
pconsole/cmd_command.py
pconsole/config.json
pconsole/console.py
pconsole/defaults.py
pconsole/file.py
pconsole/inputfield.py
pconsole/license.txt
pconsole/lines.py
pconsole/version.py
pconsole/win_convert.py
pconsole/win_symbols.json
pconsole-0.4.0.dist-info/LICENSE
pconsole-0.4.0.dist-info/METADATA
pconsole-0.4.0.dist-info/WHEEL
pconsole-0.4.0.dist-info/top_level.txt
pconsole-0.4.0.dist-info/zip-safe
pconsole-0.4.0.dist-info/RECORD
