Metadata-Version: 2.1
Name: pconsole
Version: 0.4.0
Summary: Console for panda3d application written in python
Home-page: https://github.com/l3alr0g/pconsole
Author: l3alr0g
Author-email: negreljerzy.philippe@gmail.com
License: MIT
Keywords: console,panda3d,python,gamedev
Platform: Windows
Platform: Linux
Platform: OSX
Requires-Python: >=3.5
Requires-Dist: panda3d
